[
    {
        "id": "naval-ravikant",
        "section": "citas",
        "date": "September 14, 2020",
        "title": "“El único test real de inteligencia es conseguir todo lo que te pronpongas de la vida.”",
        "description": "— Naval Ravikant...",
        "url": "blog_store/posts/citas/naval-ravikant"
    },
    {
        "id": "gestiona-tus-credenciales-como-un-ninja",
        "section": "seguridad",
        "date": "September 4, 2020",
        "title": "🔐 Gestiona tus credenciales como un ninja",
        "description": "Seguro que has pensado alguna vez que el sitema de acceso de cualquier web/app/sistema estaba simplemente diseñado contra ti. Admitámoslo, las contraseñas son un problema desde que existen. De hecho ¿Hay algo más odioso que tener que crear una nueva? Conozco muchos gilipollas y aún así me cuesta imaginarme a ninguno de ellos reposando su primer café de la mañana mientras frota sus manos...",
        "url": "blog_store/posts/seguridad/gestiona-tus-credenciales-como-un-ninja.md"
    },
    {
        "id": "hola-mundo",
        "section": "opinión",
        "date": "September 2, 2020",
        "title": "👋🏻🌎 Hola Mundo",
        "description": "> 0x000000000019d6689c085ae165831e934ff763ae46a2a6c172b3f1b60a8ce26f Dado que estás leyendo el génesis de este blog medianamente serio y nada pretensioso, me parecía un bonito tributo a mi Papá que la primera línea del primer post le corresponda al genesis block hash de nuestra contribución familiar a la humanidad (y quien quiera que la conquiste detrás): El ₿itcoin ¿Qué puedes esperar encontrar por aquí? Nada útil para el común...",
        "url": "blog_store/posts/opinión/hola-mundo.md"
    }
]